<recipes>
    ## Cloud Mica Whetstone
    <cp>338</cp>
    <recipe>
        <name>Cloud Mica Whetstone</name>
        <durability>35</durability>
        <careful_prog>205</careful_prog>
        <total_prog>376</total_prog>
        <num_mark>0</num_mark>
        <stack_goal>8</stack_goal>
    </recipe>
    <recipe>
        <name>Mythrite Nugget</name>
        <durability>40</durability>
        <careful_prog>227</careful_prog>
        <total_prog>165</total_prog>
        <num_mark>0</num_mark>
        <stack_goal>6</stack_goal>
    </recipe>

</recipes>